code/graycode_counter.v
`timescale 1ns/1ns

module graycode_counter(
    input clk,
    input reset,
    input up_down,
    output [2:0] o_bin,
    output [2:0] o_gray_code
);

reg [2:0] bin_counter = 0;

always @(posedge clk or posedge reset)
    if(reset)
        bin_counter <= 0;
    else if(up_down)
        bin_counter <= bin_counter + 1;
    else
        bin_counter <= bin_counter - 1;

assign o_bin = bin_counter;

// reg [2:0] r_gc = 0;

// always @(bin_counter)
//     case (bin_counter)
//         0 : r_gc = 3'b000;
//         1 : r_gc = 3'b001;
//         2 : r_gc = 3'b011;
//         3 : r_gc = 3'b010;
//         4 : r_gc = 3'b110;
//         5 : r_gc = 3'b111;
//         6 : r_gc = 3'b101;
//         7 : r_gc = 3'b100;
//     endcase

// assign o_gray_code = r_gc;

assign o_gray_code[2] = bin_counter[2];
assign o_gray_code[1] = bin_counter[2] ^ bin_counter[1];
assign o_gray_code[0] = bin_counter[1] ^ bin_counter[0];
endmodule

code/graycode_counter_tb.v
`timescale 1ns/1ns
`include "graycode_counter.v"

module graycode_counter_tb;
    reg clk;
    reg reset;
    reg up_down;
    wire [2:0] gray_code;
    wire [2:0] bin_count;

    graycode_counter gc(.clk(clk), .reset(reset), .up_down(up_down), .o_bin(bin_count), .o_gray_code(gray_code));

    always #1 clk = ~clk;
    always #10 up_down = ~up_down;

    initial begin

        $dumpfile("graycode_counter_tb.vcd");
        $dumpvars(0,graycode_counter_tb);

        clk = 0;
        up_down = 1;
        reset = 1;
        #2;
        reset = 0;


        #40;
        $display("Test complete");
        $finish;
    end

endmodule

code/graycode_counter_tb.vcd
$date
	Sat May 11 03:48:14 2024
$end
$version
	Icarus Verilog
$end
$timescale
	1ns
$end
$scope module graycode_counter_tb $end
$var wire 3 ! gray_code [2:0] $end
$var wire 3 " bin_count [2:0] $end
$var reg 1 # clk $end
$var reg 1 $ reset $end
$var reg 1 % up_down $end
$scope module gc $end
$var wire 1 # clk $end
$var wire 3 & o_bin [2:0] $end
$var wire 1 $ reset $end
$var wire 1 % up_down $end
$var wire 3 ' o_gray_code [2:0] $end
$var reg 3 ( bin_counter [2:0] $end
$upscope $end
$upscope $end
$enddefinitions $end
$comment Show the parameter values. $end
$dumpall
$end
#0
$dumpvars
b0 (
b0 '
b0 &
1%
1$
0#
b0 "
b0 !
$end
#1
1#
#2
0#
0$
#3
b1 !
b1 '
b1 "
b1 &
b1 (
1#
#4
0#
#5
b11 !
b11 '
b10 "
b10 &
b10 (
1#
#6
0#
#7
b10 !
b10 '
b11 "
b11 &
b11 (
1#
#8
0#
#9
b110 !
b110 '
b100 "
b100 &
b100 (
1#
#10
0#
0%
#11
b10 !
b10 '
b11 "
b11 &
b11 (
1#
#12
0#
#13
b11 !
b11 '
b10 "
b10 &
b10 (
1#
#14
0#
#15
b1 !
b1 '
b1 "
b1 &
b1 (
1#
#16
0#
#17
b0 !
b0 '
b0 "
b0 &
b0 (
1#
#18
0#
#19
b100 !
b100 '
b111 "
b111 &
b111 (
1#
#20
0#
1%
#21
b0 !
b0 '
b0 "
b0 &
b0 (
1#
#22
0#
#23
b1 !
b1 '
b1 "
b1 &
b1 (
1#
#24
0#
#25
b11 !
b11 '
b10 "
b10 &
b10 (
1#
#26
0#
#27
b10 !
b10 '
b11 "
b11 &
b11 (
1#
#28
0#
#29
b110 !
b110 '
b100 "
b100 &
b100 (
1#
#30
0#
0%
#31
b10 !
b10 '
b11 "
b11 &
b11 (
1#
#32
0#
#33
b11 !
b11 '
b10 "
b10 &
b10 (
1#
#34
0#
#35
b1 !
b1 '
b1 "
b1 &
b1 (
1#
#36
0#
#37
b0 !
b0 '
b0 "
b0 &
b0 (
1#
#38
0#
#39
b100 !
b100 '
b111 "
b111 &
b111 (
1#
#40
0#
1%
#41
b0 !
b0 '
b0 "
b0 &
b0 (
1#
