code/minority.v
module minority(A,B,C,Y);
    input A,B,C;
    output Y;

    assign Y = ~A & ~B | ~A & ~C | ~B & ~C;
endmodule

code/minority_tb.v
`timescale 1ns/1ns
`include "minority.v"

module minority_tb;

    reg A,B,C;
    wire Y;

    minority uut(A,B,C,Y);

    initial begin
        $dumpfile("minority_tb.vcd");
        $dumpvars(0,minority_tb);
        {A,B,C} = 3'd0; #20;
        {A,B,C} = 3'd1; #20;
        {A,B,C} = 3'd2; #20;
        {A,B,C} = 3'd3; #20;
        {A,B,C} = 3'd4; #20;
        {A,B,C} = 3'd5; #20;
        {A,B,C} = 3'd6; #20;
        {A,B,C} = 3'd7; #20;
        $display("Test is complete!");
    end

endmodule

code/minority_tb.vcd
$date
	Fri May 10 23:00:59 2024
$end
$version
	Icarus Verilog
$end
$timescale
	1ns
$end
$scope module minority_tb $end
$var wire 1 ! Y $end
$var reg 1 " A $end
$var reg 1 # B $end
$var reg 1 $ C $end
$scope module uut $end
$var wire 1 " A $end
$var wire 1 # B $end
$var wire 1 $ C $end
$var wire 1 ! Y $end
$upscope $end
$upscope $end
$enddefinitions $end
$comment Show the parameter values. $end
$dumpall
$end
#0
$dumpvars
0$
0#
0"
1!
$end
#20
1$
#40
1#
0$
#60
0!
1$
#80
1!
1"
0#
0$
#100
0!
1$
#120
1#
0$
#140
1$
